veeink_mcp_server/__init__.py
veeink_mcp_server-0.2.0.dist-info/WHEEL
veeink_mcp_server-0.2.0.dist-info/entry_points.txt
veeink_mcp_server-0.2.0.dist-info/METADATA
veeink_mcp_server-0.2.0.dist-info/RECORD
