Metadata-Version: 2.3
Name: veeink-mcp-server
Version: 0.2.0
Summary: Veeink的MCP服务
Author: wlf
Author-email: wlf <fwl7747@126.com>
Requires-Dist: mcp[cli]>=1.13.1
Requires-Python: >=3.13
